{
  "collectionName": "components_home_components_home_tiles",
  "info": {
    "name": "HomeTile",
    "icon": "ad"
  },
  "options": {},
  "attributes": {
    "header_en": {
      "type": "string",
      "private": false,
      "required": true
    },
    "path": {
      "type": "string"
    },
    "icon": {
      "model": "file",
      "via": "related",
      "allowedTypes": [
        "images"
      ],
      "plugin": "upload",
      "required": false
    },
    "header_fr": {
      "type": "string",
      "required": true
    },
    "header_short_en": {
      "type": "string"
    },
    "header_short_fr": {
      "type": "string"
    },
    "sub_pages": {
      "collection": "sub-page"
    },
    "content_en": {
      "type": "richtext"
    },
    "content_fr": {
      "type": "richtext"
    }
  }
}
